{"skeleton":{"hash":"I2z0zbBIvnOYbt3dndM4MFNRD/s","spine":"3.6.53","width":88.44,"height":109.1,"images":"../野獣先輩BB作成キット/"},"bones":[{"name":"root"},{"name":"bone","parent":"root","x":-6.74,"y":65.53,"scaleX":1.823,"scaleY":1.823},{"name":"kawaikao","parent":"bone","length":98.37,"rotation":84.39,"x":-0.18,"y":5.15},{"name":"kawaikao3","parent":"kawaikao","length":18.4,"rotation":100.6,"x":37.93,"y":12.67},{"name":"kawaikao4","parent":"kawaikao","length":31.33,"rotation":-84.39,"x":39.11,"y":-6.71},{"name":"kawaikao5","parent":"kawaikao","length":35.19,"rotation":25.42,"x":57.83,"y":-38.86},{"name":"kawaikao6","parent":"kawaikao","length":40.79,"rotation":-29.26,"x":57.77,"y":34.65}],"slots":[{"name":"kawaikao","bone":"kawaikao6","attachment":"kawaikao"}],"skins":{"default":{"kawaikao":{"kawaikao":{"type":"mesh","uvs":[1,0.17385,1,0.44482,1,0.4711,0.56201,0.96227,0.15585,0.93397,0.05812,0.53749,0.07675,0.37949,0.08055,0.34732,0.1098,0.09929,0.50428,0,0.4193,0.68412,0.68416,0.39907,0.70683,0.38617],"triangles":[2,11,12,2,3,11,12,1,2,12,0,1,12,9,0,5,6,10,6,7,10,9,7,8,4,10,3,3,10,11,4,5,10,10,7,11,7,9,11,11,9,12],"vertices":[1,5,24.64,-21.09,1,2,4,45.31,15.1,0.04123,5,-4.26,-10.68,0.95877,2,4,45.31,12.12,0.09065,5,-7.06,-9.67,0.90935,2,2,-3.84,-15.13,0.93443,4,4.18,-43.57,0.06557,2,2,-4.38,23.14,0.79187,3,18.08,39.65,0.20813,2,3,23.31,-5.93,0.83286,6,-16.95,-7.18,0.16714,2,3,20,-23.62,0.00723,6,-1.25,1.62,0.99277,1,6,1.94,3.41,1,1,6,26.58,17.24,1,3,2,104.21,0.92,0.971,6,57,-6.72,0.02699,5,58.96,16.03,0.00202,2,2,26.23,1.29,0.97427,3,-9.03,13.59,0.02573,3,2,60.83,-20.31,0.29393,4,15.65,20.28,0.22811,5,10.67,15.47,0.47796,3,2,62.49,-22.28,0.23969,4,17.78,21.75,0.17948,5,11.33,12.97,0.58084],"hull":10,"edges":[0,18,16,18,10,8,4,6,8,6,14,16,14,20,20,22,0,2,2,4,24,2,10,12,12,14,12,20],"width":241,"height":291}}}},"animations":{"animation":{"bones":{"bone":{"rotate":[{"time":0,"angle":0,"curve":"stepped"},{"time":3.3333,"angle":0}],"translate":[{"time":0,"x":0,"y":0},{"time":1.6667,"x":0,"y":-21.55},{"time":3.3333,"x":0,"y":0}]},"kawaikao":{"rotate":[{"time":0,"angle":0},{"time":1.7333,"angle":7.5},{"time":3.3333,"angle":0}],"translate":[{"time":0,"x":0,"y":0,"curve":"stepped"},{"time":3.3333,"x":0,"y":0}]},"kawaikao3":{"rotate":[{"time":0,"angle":0},{"time":1.4333,"angle":9.12},{"time":1.8333,"angle":10.2},{"time":3.3333,"angle":0}],"translate":[{"time":0,"x":0,"y":0,"curve":"stepped"},{"time":3.3333,"x":0,"y":0}]},"kawaikao4":{"rotate":[{"time":0,"angle":0},{"time":1.7333,"angle":-21.08},{"time":2,"angle":-20.4},{"time":3.3333,"angle":0}],"translate":[{"time":0,"x":0,"y":0,"curve":"stepped"},{"time":3.3333,"x":0,"y":0}]},"kawaikao5":{"rotate":[{"time":0,"angle":0},{"time":1.8333,"angle":8.62},{"time":3.3333,"angle":0}],"translate":[{"time":0,"x":0,"y":0,"curve":"stepped"},{"time":3.3333,"x":0,"y":0}]},"kawaikao6":{"rotate":[{"time":0,"angle":0},{"time":1.3333,"angle":8.67},{"time":3.3333,"angle":0}],"translate":[{"time":0,"x":0,"y":0,"curve":"stepped"},{"time":3.3333,"x":0,"y":0}]}}}}}